umlcharter/__init__.py
umlcharter/charts/__init__.py
umlcharter/charts/common.py
umlcharter/charts/graph_diagram.py
umlcharter/charts/sequence_diagram.py
umlcharter/generators/__init__.py
umlcharter/generators/base.py
umlcharter/generators/d2/__init__.py
umlcharter/generators/d2/d2.py
umlcharter/generators/d2/sequence_diagram.py
umlcharter/generators/graphviz/__init__.py
umlcharter/generators/graphviz/graph_diagram.py
umlcharter/generators/graphviz/graphviz.py
umlcharter/generators/mermaid/__init__.py
umlcharter/generators/mermaid/graph_diagram.py
umlcharter/generators/mermaid/mermaid.py
umlcharter/generators/mermaid/sequence_diagram.py
umlcharter/generators/plantuml/__init__.py
umlcharter/generators/plantuml/graph_diagram.py
umlcharter/generators/plantuml/plantuml.py
umlcharter/generators/plantuml/sequence_diagram.py
umlcharter/generators/sequencediagramorg/__init__.py
umlcharter/generators/sequencediagramorg/sequence_diagram.py
umlcharter/generators/sequencediagramorg/sequencediagramorg.py
umlcharter-1.1.6.dist-info/licenses/LICENSE
umlcharter-1.1.6.dist-info/METADATA
umlcharter-1.1.6.dist-info/WHEEL
umlcharter-1.1.6.dist-info/top_level.txt
umlcharter-1.1.6.dist-info/RECORD
