Metadata-Version: 2.4
Name: umlcharter
Version: 1.1.6
Summary: Python package for quick diagrams creation without a need to learn new DSL
Home-page: https://github.com/mikalaiyurkin/charter
Author: Mikalai Yurkin
Author-email: yurkin.mikalai@gmail.com
Classifier: Programming Language :: Python :: 3
Classifier: Programming Language :: Python :: 3.9
Classifier: Programming Language :: Python :: 3.10
Classifier: Programming Language :: Python :: 3.11
Classifier: Programming Language :: Python :: 3.12
Classifier: Programming Language :: Python :: 3.13
Classifier: Programming Language :: Python :: 3.14
Classifier: License :: OSI Approved :: MIT License
Classifier: Operating System :: OS Independent
Classifier: Intended Audience :: Developers
Classifier: Topic :: Software Development
Requires-Python: >=3.9
License-File: LICENSE
Provides-Extra: dev
Requires-Dist: pytest; extra == "dev"
Requires-Dist: pytest-cov; extra == "dev"
Requires-Dist: pre-commit; extra == "dev"
Dynamic: author
Dynamic: author-email
Dynamic: classifier
Dynamic: description
Dynamic: description-content-type
Dynamic: home-page
Dynamic: license-file
Dynamic: provides-extra
Dynamic: requires-python
Dynamic: summary
